jackaudiotools/carla/carxp2lv2presets.py
jackaudiotools/carla/loadcarxp.py
jackaudiotools/jackdbus/jackmonitor.py
jackaudiotools/lv2/grep.py
jackaudiotools/lv2/list_plugin_presets.py
jackaudiotools/lv2/plugin_info.py
jackaudiotools/lv2/plugin_uris.py
jackaudiotools/transport/midi_to_transport.py
jackaudiotools/transport/rtmidi_to_transport.py
jackaudiotools/transport/timebase_master.py
jackaudiotools/transport/transporter.py
jack_audio_tools-0.4.1.dist-info/LICENSE
jack_audio_tools-0.4.1.dist-info/METADATA
jack_audio_tools-0.4.1.dist-info/WHEEL
jack_audio_tools-0.4.1.dist-info/entry_points.txt
jack_audio_tools-0.4.1.dist-info/top_level.txt
jack_audio_tools-0.4.1.dist-info/RECORD
