Metadata-Version: 2.1
Name: jack-audio-tools
Version: 0.4.1
Summary: A collection of utilities and tools for the JACK audio ecosystem
Home-page: https://github.com/SpotlightKid/jack-audio-tools
Author: Christopher Arndt
Author-email: info@chrisarndt.de
License: MIT License
Keywords: jack,jackaudio,LV2,carla,MIDI
Classifier: Development Status :: 4 - Beta
Classifier: Environment :: Console
Classifier: Operating System :: POSIX
Classifier: License :: OSI Approved :: MIT License
Classifier: Programming Language :: Python
Classifier: Programming Language :: Python :: 3 :: Only
Classifier: Programming Language :: Python :: 3.9
Classifier: Programming Language :: Python :: 3.10
Classifier: Programming Language :: Python :: 3.11
Classifier: Topic :: Multimedia :: Sound/Audio
Requires-Python: >=3
License-File: LICENSE
Requires-Dist: JACK-Client (>=0.5.0)
Provides-Extra: dbus
Requires-Dist: PyGObject ; extra == 'dbus'
Requires-Dist: dbus-python ; extra == 'dbus'
Provides-Extra: rdflib
Requires-Dist: rdflib ; extra == 'rdflib'
Provides-Extra: rtmidi
Requires-Dist: python-rtmidi ; extra == 'rtmidi'
